aws_fusion/__init__.py
aws_fusion/app.py
aws_fusion/aws/__init__.py
aws_fusion/aws/api.py
aws_fusion/aws/assume_role.py
aws_fusion/aws/session.py
aws_fusion/commands/__init__.py
aws_fusion/commands/config_switch.py
aws_fusion/commands/iam_user_credentials.py
aws_fusion/commands/init.py
aws_fusion/commands/okta.py
aws_fusion/commands/open_browser.py
aws_fusion/okta/__init__.py
aws_fusion/okta/api.py
aws_fusion-1.7.5.data/scripts/_awsp
aws_fusion-1.7.5.data/scripts/_awsp.ps1
aws_fusion-1.7.5.data/scripts/_awsr
aws_fusion-1.7.5.data/scripts/_awsr.ps1
aws_fusion-1.7.5.dist-info/LICENSE
aws_fusion-1.7.5.dist-info/METADATA
aws_fusion-1.7.5.dist-info/WHEEL
aws_fusion-1.7.5.dist-info/entry_points.txt
aws_fusion-1.7.5.dist-info/top_level.txt
aws_fusion-1.7.5.dist-info/RECORD
