Metadata-Version: 2.1
Name: aws-fusion
Version: 1.7.5
Summary: Unified CLI tool for streamlined AWS operations
Home-page: https://github.com/snigdhasjg/aws-fusion
Author: Snigdhajyoti Ghosh
Author-email: aws-fusion.support@snigji.com
License: MIT License
Keywords: aws,aws-sdk,aws-cli,aws-authentication,aws-sdk-python,aws-auth
Classifier: Programming Language :: Python :: 3
Classifier: License :: OSI Approved :: MIT License
Classifier: Intended Audience :: Developers
Classifier: Intended Audience :: System Administrators
Classifier: Operating System :: OS Independent
Classifier: Development Status :: 4 - Beta
Classifier: Topic :: Utilities
License-File: LICENSE
Requires-Dist: boto3>=1.29
Requires-Dist: pyperclip>=1.8
Requires-Dist: keyring>=24.3
Requires-Dist: beautifulsoup4>=4.12
Requires-Dist: requests>=2.31
Requires-Dist: inquirer>=3.1
